setup.py
kddcup2015_cli/__init__.py
kddcup2015_cli/config.py
kddcup2015_cli/download.py
kddcup2015_cli/main.py
kddcup2015_cli/rank.py
kddcup2015_cli/score.py
kddcup2015_cli/submit.py
kddcup2015_cli.egg-info/PKG-INFO
kddcup2015_cli.egg-info/SOURCES.txt
kddcup2015_cli.egg-info/dependency_links.txt
kddcup2015_cli.egg-info/entry_points.txt
kddcup2015_cli.egg-info/namespace_packages.txt
kddcup2015_cli.egg-info/not-zip-safe
kddcup2015_cli.egg-info/pbr.json
kddcup2015_cli.egg-info/requires.txt
kddcup2015_cli.egg-info/top_level.txt