Metadata-Version: 1.1
Name: kddcup2015-cli
Version: 0.1.3
Summary: An unofficial command line tool for KDD Cup 2015.
Home-page: https://github.com/floydsoft/kddcup2015-cli
Author: floydsoft
Author-email: floydsoft@gmail.com
License: UNKNOWN
Download-URL: https://github.com/floydsoft/kddcup2015-cli/tarball/master
Platform: Any
Classifier: Development Status :: 3 - Alpha
Classifier: License :: OSI Approved :: MIT License
Classifier: Programming Language :: Python
Classifier: Programming Language :: Python :: 2
Classifier: Programming Language :: Python :: 2.7
Classifier: Programming Language :: Python :: 3
Classifier: Programming Language :: Python :: 3.4
Classifier: Intended Audience :: Developers
Classifier: Environment :: Console
